kattis_cli/.kattis-cli.toml
kattis_cli/__init__.py
kattis_cli/client.py
kattis_cli/download.py
kattis_cli/fireworks.py
kattis_cli/kattis.py
kattis_cli/kattis_setup.py
kattis_cli/kattis_templates/__init__.py
kattis_cli/kattis_templates/main/c.txt
kattis_cli/kattis_templates/main/cpp.txt
kattis_cli/kattis_templates/main/java.txt
kattis_cli/kattis_templates/main/python.txt
kattis_cli/kattis_templates/main/python3.txt
kattis_cli/kattis_templates/project_structure/c/Makefile
kattis_cli/kattis_templates/project_structure/c/src/problemid/problemid.c
kattis_cli/kattis_templates/project_structure/c/tests/test_problemid.c
kattis_cli/kattis_templates/project_structure/cpp/Makefile
kattis_cli/kattis_templates/project_structure/cpp/src/problemid.cpp
kattis_cli/kattis_templates/project_structure/cpp/tests/test_problemid.cpp
kattis_cli/kattis_templates/project_structure/java/src/problemid.java
kattis_cli/kattis_templates/project_structure/java/tests/tests_problemid.java
kattis_cli/kattis_templates/project_structure/python/Makefile
kattis_cli/kattis_templates/project_structure/python/src/problemid.py
kattis_cli/kattis_templates/project_structure/python/tests/__init__.py
kattis_cli/kattis_templates/project_structure/python/tests/test_problemid.py
kattis_cli/kattis_templates/project_structure/python3/Makefile
kattis_cli/kattis_templates/project_structure/python3/src/problemid.py
kattis_cli/kattis_templates/project_structure/python3/tests/__init__.py
kattis_cli/kattis_templates/project_structure/python3/tests/test_problemid.py
kattis_cli/main.py
kattis_cli/settings.py
kattis_cli/solution_tester.py
kattis_cli/template.py
kattis_cli/ui.py
kattis_cli/utils/__init__.py
kattis_cli/utils/config.py
kattis_cli/utils/languages.py
kattis_cli/utils/run_program.py
kattis_cli/utils/utility.py
kattis_cli-1.2.4.dist-info/METADATA
kattis_cli-1.2.4.dist-info/WHEEL
kattis_cli-1.2.4.dist-info/entry_points.txt
kattis_cli-1.2.4.dist-info/licenses/LICENSE
kattis_cli-1.2.4.dist-info/RECORD
