Metadata-Version: 2.4
Name: kattis-cli
Version: 1.2.4
Summary: A command-line tool for Kattis
License-File: LICENSE
Author: Ram Basnet
Author-email: rbasnet@coloradomesa.edu
Requires-Python: >=3.10.0,<4.0.0
Classifier: Programming Language :: Python :: 3
Classifier: License :: OSI Approved :: MIT License
Classifier: Operating System :: OS Independent
Requires-Dist: beautifulsoup4 (>=4.12.2,<5.0.0)
Requires-Dist: click (>=8.1.7,<9.0.0)
Requires-Dist: lxml (>=6.0.1,<7.0.0)
Requires-Dist: pyyaml (>=6.0.1,<7.0.0)
Requires-Dist: requests (>=2.31.0,<3.0.0)
Requires-Dist: rich (>=13.6.0,<14.0.0)
Requires-Dist: tomlkit (>=0.12.2,<0.13.0)
Requires-Dist: trogon (>=0.6.0,<0.7.0)
Project-URL: Bug Tracker, https://github.com/rambasnet/kattis-cli/issues
Project-URL: Homepage, https://github.com/rambasnet/kattis-cli
